aiosignald/__init__.py
aiosignald/error.py
aiosignald/exc.py
aiosignald/generated.py
aiosignald/py.typed
aiosignald/util.py
aiosignald-0.3.7.dist-info/LICENSE
aiosignald-0.3.7.dist-info/METADATA
aiosignald-0.3.7.dist-info/WHEEL
aiosignald-0.3.7.dist-info/RECORD
