Metadata-Version: 2.1
Name: aiosignald
Version: 0.3.7
Summary: Python bindings for signald
Home-page: https://git.sr.ht/~nicoco/aiosignald
License: AGPL-3.0-or-later
Author: Nicolas Cedilnik
Author-email: nicoco@nicoco.fr
Requires-Python: >=3.8,<4
Classifier: License :: OSI Approved :: GNU Affero General Public License v3 or later (AGPLv3+)
Classifier: Programming Language :: Python :: 3
Classifier: Programming Language :: Python :: 3.8
Classifier: Programming Language :: Python :: 3.9
Classifier: Programming Language :: Python :: 3.10
Classifier: Programming Language :: Python :: 3.11
